asg_scaling_manager/__init__.py
asg_scaling_manager/aws_client.py
asg_scaling_manager/cli.py
asg_scaling_manager/logging.py
asg_scaling_manager/models.py
asg_scaling_manager/planner.py
asg_scaling_manager/selector.py
asg_scaling_manager-0.1.0.dist-info/licenses/LICENSE
asg_scaling_manager-0.1.0.dist-info/METADATA
asg_scaling_manager-0.1.0.dist-info/WHEEL
asg_scaling_manager-0.1.0.dist-info/entry_points.txt
asg_scaling_manager-0.1.0.dist-info/top_level.txt
asg_scaling_manager-0.1.0.dist-info/RECORD
