Metadata-Version: 2.4
Name: asg-scaling-manager
Version: 0.1.0
Summary: CLI library to manage AWS ASG desired/min/max capacity by tag filters
Author: Grzegorz K
License-Expression: MIT
Project-URL: Homepage, https://github.com/grzes-94/asg-scaling-manage
Project-URL: Repository, https://github.com/grzes-94/asg-scaling-manage
Project-URL: Issues, https://github.com/grzes-94/asg-scaling-manage/issues
Keywords: aws,autoscaling,asg,cli,eks
Classifier: Development Status :: 4 - Beta
Classifier: Intended Audience :: Developers
Classifier: Intended Audience :: System Administrators
Classifier: Operating System :: OS Independent
Classifier: Programming Language :: Python :: 3
Classifier: Programming Language :: Python :: 3.9
Classifier: Programming Language :: Python :: 3.10
Classifier: Programming Language :: Python :: 3.11
Classifier: Programming Language :: Python :: 3.12
Classifier: Topic :: System :: Systems Administration
Classifier: Topic :: Utilities
Requires-Python: >=3.9
License-File: LICENSE
Requires-Dist: boto3>=1.34
Requires-Dist: typer>=0.12
Requires-Dist: pydantic>=2.7
Requires-Dist: structlog>=24.1
Dynamic: license-file
